galaxy/web_client/__init__.py
galaxy/web_client/client_build_hash.txt
galaxy/web_client/install.py
galaxy/web_client/dist/00950d3d0eabc9b79c13.png
galaxy/web_client/dist/00b14a051b8ec5846ca4.png
galaxy/web_client/dist/0108e89c9003e8c14ea3.woff
galaxy/web_client/dist/015bb398cc86c8e2c532.png
galaxy/web_client/dist/02271ec5cb9f5b4588ac.woff
galaxy/web_client/dist/073b3402d036714b4370.woff
galaxy/web_client/dist/0a09dd8bcca1e540a97f.png
galaxy/web_client/dist/0c3b8929d377c0e9b2f3.woff
galaxy/web_client/dist/0c708255f16de429468f.png
galaxy/web_client/dist/1079.bundled.js
galaxy/web_client/dist/1103.bundled.js
galaxy/web_client/dist/1109.bundled.js
galaxy/web_client/dist/1152.bundled.js
galaxy/web_client/dist/1158.bundled.js
galaxy/web_client/dist/1192.bundled.js
galaxy/web_client/dist/1223.bundled.js
galaxy/web_client/dist/1246.bundled.js
galaxy/web_client/dist/1248.bundled.js
galaxy/web_client/dist/1280.bundled.js
galaxy/web_client/dist/1316.bundled.js
galaxy/web_client/dist/1354.bundled.js
galaxy/web_client/dist/1360.bundled.js
galaxy/web_client/dist/1444303e4f0c0f62fa36.png
galaxy/web_client/dist/1464.bundled.js
galaxy/web_client/dist/1487.bundled.js
galaxy/web_client/dist/152.bundled.js
galaxy/web_client/dist/1534.bundled.js
galaxy/web_client/dist/1551f4f60c37af51121f.woff2
galaxy/web_client/dist/1581.bundled.js
galaxy/web_client/dist/1583.bundled.js
galaxy/web_client/dist/16.bundled.js
galaxy/web_client/dist/1651.bundled.js
galaxy/web_client/dist/1658.bundled.js
galaxy/web_client/dist/1661.bundled.js
galaxy/web_client/dist/1688.bundled.js
galaxy/web_client/dist/169.bundled.js
galaxy/web_client/dist/172d3529b26f8cedef6b.woff2
galaxy/web_client/dist/175327482730212e7000.png
galaxy/web_client/dist/1759.bundled.js
galaxy/web_client/dist/178.bundled.js
galaxy/web_client/dist/17aaaa49460f37c9589a.png
galaxy/web_client/dist/186.bundled.js
galaxy/web_client/dist/1875.bundled.js
galaxy/web_client/dist/188.bundled.js
galaxy/web_client/dist/193.bundled.js
galaxy_web_client-25.0.3.dist-info/METADATA
galaxy_web_client-25.0.3.dist-info/WHEEL
galaxy_web_client-25.0.3.dist-info/entry_points.txt
galaxy_web_client-25.0.3.dist-info/top_level.txt
galaxy_web_client-25.0.3.dist-info/RECORD
